flatcitybuf-0.2.0.dist-info/METADATA
flatcitybuf-0.2.0.dist-info/WHEEL
flatcitybuf/__init__.py
flatcitybuf/flatcitybuf.cp39-win_amd64.pyd
flatcitybuf-0.2.0.dist-info/RECORD
