Metadata-Version: 2.4
Name: flatcitybuf
Version: 0.2.0
Classifier: Development Status :: 4 - Beta
Classifier: Intended Audience :: Developers
Classifier: Intended Audience :: Science/Research
Classifier: License :: OSI Approved :: MIT License
Classifier: Programming Language :: Python :: 3
Classifier: Programming Language :: Python :: 3.8
Classifier: Programming Language :: Python :: 3.9
Classifier: Programming Language :: Python :: 3.10
Classifier: Programming Language :: Python :: 3.11
Classifier: Programming Language :: Python :: 3.12
Classifier: Programming Language :: Rust
Classifier: Topic :: Scientific/Engineering :: GIS
Classifier: Topic :: Software Development :: Libraries :: Python Modules
Classifier: Operating System :: OS Independent
Requires-Dist: pytest>=8.3.5
Requires-Dist: pytest-asyncio>=0.24.0
Requires-Dist: pytest>=7.0 ; extra == 'test'
Requires-Dist: pytest-asyncio>=0.21.0 ; extra == 'test'
Requires-Dist: ruff>=0.1.0 ; extra == 'dev'
Requires-Dist: mypy>=1.0 ; extra == 'dev'
Requires-Dist: maturin>=1.0 ; extra == 'dev'
Provides-Extra: test
Provides-Extra: dev
Summary: Python bindings for FlatCityBuf - a cloud-optimized binary format for 3D city models
Keywords: gis,3d,cityjson,citymodel,flatbuffers
Author: HideBa
License: MIT
Requires-Python: >=3.8.1
Project-URL: Bug Tracker, https://github.com/cityjson/flatcitybuf/issues
Project-URL: Source Code, https://github.com/cityjson/flatcitybuf
Project-URL: Documentation, https://github.com/cityjson/flatcitybuf/blob/main/README.md
